web_novel_scraper/__init__.py
web_novel_scraper/__main__.py
web_novel_scraper/config_manager.py
web_novel_scraper/decode.py
web_novel_scraper/file_manager.py
web_novel_scraper/logger_manager.py
web_novel_scraper/models.py
web_novel_scraper/novel_scraper.py
web_novel_scraper/request_manager.py
web_novel_scraper/utils.py
web_novel_scraper/version.py
web_novel_scraper/custom_processor/__init__.py
web_novel_scraper/custom_processor/custom_processor.py
web_novel_scraper/custom_processor/sites/fanmtl.py
web_novel_scraper/custom_processor/sites/genesis.py
web_novel_scraper/custom_processor/sites/novelbin.py
web_novel_scraper/custom_processor/sites/novelhi.py
web_novel_scraper/custom_processor/sites/royalroad.py
web_novel_scraper/decode_guide/decode_guide.json
web_novel_scraper-2.1.11.dist-info/METADATA
web_novel_scraper-2.1.11.dist-info/WHEEL
web_novel_scraper-2.1.11.dist-info/entry_points.txt
web_novel_scraper-2.1.11.dist-info/RECORD
