Metadata-Version: 2.4
Name: web-novel-scraper
Version: 2.1.11
Summary: Python tool that allows you to scrape web novels from various sources and save them to more readable formats like EPUB.
Project-URL: Homepage, https://github.com/ImagineBrkr/web-novel-scraper
Project-URL: Documentation, https://web-novel-scraper.readthedocs.io
Project-URL: Repository, https://github.com/ImagineBrkr/web-novel-scraper.git
Author-email: ImagineBrkr <salvattore_25@hotmail.com>
Keywords: Novel Downloader,Scraper,Web Novel,Web Novel Downloader,Web Novel Scraper
Requires-Python: >=3.10
Requires-Dist: bs4>=0.0.2
Requires-Dist: click<9,>=8.0
Requires-Dist: dataclasses-json<1,>=0.6.7
Requires-Dist: ebooklib<1,>=0.18
Requires-Dist: ftfy<7,>=6.3.1
Requires-Dist: platformdirs
Requires-Dist: python-dotenv
Requires-Dist: requests
